django_shortuuid/__init__.py
django_shortuuid/fields.py
django_shortuuid/py.typed
django_shortuuid-0.1.2.dist-info/WHEEL
django_shortuuid-0.1.2.dist-info/METADATA
django_shortuuid-0.1.2.dist-info/RECORD
