Metadata-Version: 2.3
Name: django-shortuuid
Version: 0.1.2
Summary: A modern, Django model field for generating short, unique, URL-safe UUIDs using the shortuuid lib.
Keywords: django,shortuuid,uuid,field,model,unique-id
Author: stabldev
Author-email: stabldev <thestabldev@gmail.com>
License: MIT
Classifier: Development Status :: 4 - Beta
Classifier: Framework :: Django
Classifier: Framework :: Django :: 5.2
Classifier: Intended Audience :: Developers
Classifier: License :: OSI Approved :: MIT License
Classifier: Operating System :: OS Independent
Classifier: Programming Language :: Python
Classifier: Programming Language :: Python :: 3
Classifier: Programming Language :: Python :: 3.13
Classifier: Topic :: Software Development :: Libraries :: Python Modules
Requires-Dist: django>=5.2.6
Requires-Dist: shortuuid>=1.0.13
Requires-Python: >=3.13
Project-URL: bug-tracker, https://github.com/stabldev/django-shortuuid/issues
Project-URL: documentation, https://github.com/stabldev/django-shortuuid#readme
Project-URL: homepage, https://github.com/stabldev/django-shortuuid
Project-URL: repository, https://github.com/stabldev/django-shortuuid
